CHANGES.rst
wordview/__init__.py
wordview/anomaly/__init__.py
wordview/anomaly/gaussianize.py
wordview/anomaly/normaldist.py
wordview/bias_analysis/__init__.py
wordview/bias_analysis/bias.py
wordview/bias_analysis/bias_terms.py
wordview/chat_ui/chat.html
wordview/clustering/__init__.py
wordview/clustering/cluster.py
wordview/io/dataframe_reader.py
wordview/mwes/__init__.py
wordview/mwes/association_measures.py
wordview/mwes/mwe.py
wordview/mwes/patterns.py
wordview/preprocessing/__init__.py
wordview/preprocessing/cleaning.py
wordview/preprocessing/count.py
wordview/text_analysis/__init__.py
wordview/text_analysis/core.py
wordview/text_analysis/wrapper.py
wordview-1.4.0.dist-info/LICENSE
wordview-1.4.0.dist-info/METADATA
wordview-1.4.0.dist-info/WHEEL
wordview-1.4.0.dist-info/RECORD
